[
  {
    "version": "3.9.9",
    "stable": true,
    "release_url": "",
    "files": [
      {
        "filename": "python-3.9.9-linux-24.04-ppc64le.tar.gz",
        "arch": "ppc64le",
        "platform": "linux",
        "platform_version": "24.04",
        "download_url": "https://github.com/adilhusain-s/actions-runner-python-versions/releases/download/3.9.9/python-3.9.9-linux-24.04-ppc64le.tar.gz"
      },
      {
        "filename": "python-3.9.9-linux-22.04-ppc64le.tar.gz",
        "arch": "ppc64le",
        "platform": "linux",
        "platform_version": "22.04",
        "download_url": "https://github.com/adilhusain-s/actions-runner-python-versions/releases/download/3.9.9/python-3.9.9-linux-22.04-ppc64le.tar.gz"
      }
    ]
  }
]